lazypp/__init__.py
lazypp/dummy_output.py
lazypp/file_objects.py
lazypp/task.py
lazypp-0.2.0.dist-info/METADATA
lazypp-0.2.0.dist-info/WHEEL
lazypp-0.2.0.dist-info/top_level.txt
lazypp-0.2.0.dist-info/RECORD
