Metadata-Version: 2.1
Name: lazypp
Version: 0.2.0
Summary: A Python package named lazypp
Author: Gen Fujimoto
Requires-Python: >=3.11
Requires-Dist: rich
Requires-Dist: xxhash
Provides-Extra: tests
Requires-Dist: pytest; extra == "tests"
